fitscube/__init__.py
fitscube/_version.py
fitscube/asyncio.py
fitscube/bounding_box.py
fitscube/cli.py
fitscube/combine_fits.py
fitscube/exceptions.py
fitscube/extract.py
fitscube/logging.py
fitscube/version.pyi
fitscube-2.3.0.dist-info/METADATA
fitscube-2.3.0.dist-info/WHEEL
fitscube-2.3.0.dist-info/entry_points.txt
fitscube-2.3.0.dist-info/licenses/LICENSE
fitscube-2.3.0.dist-info/RECORD
